<?xml version="1.0" encoding="UTF-8"?>
<krpano version="1.17"
        onstart="startup"
        logkey="false"
        bgcolor="#ffffff"
        projectfloorplanurl="%FIRSTXML%/floorplan/park.png"
        projecttitleid="project_title"
        projectdescriptionid="">

  <!-- generated by Panotour Pro V2.0.0 64bits : 01-08-2015 00-48-00 -->
  <!-- Plugins and Spot Styles -->
  <include url="%FIRSTXML%/ARTW_skin.xml"/>
  <!-- Core actions -->
  <include url="%FIRSTXML%/ARTW_core.xml"/>
  <!-- Tour Messages -->
  <include url="%FIRSTXML%/ARTW_messages_en.xml"/>

  <action name="startup">
    if (s !== null, if (startscene === null, set(startscene, get(s));); );
    if (startscene === null,
      set(startscene, pano44);
    );
    mainloadscene(get(startscene));
    if (h !== null,
      if (v !== null,
        if (f !== null,
          lookat(get(h), get(v), get(f));
         ,
          lookat(get(h), get(v));
        );
      );
    );
  </action>

  <!-- 14 Groups -->

  <!-- Group Group 58 : 1 panoramas -->
  

<!-- **** @PanoName="1" @PanoFile="F:/ПАНОРАМА/ArtPicnic/ARTPICNIC2/HDR/ALL/A.jpeg" **** -->
<scene name="pano44"
       heading="-3.39999999999981"
       thumburl="%FIRSTXML%/_1_44/thumbnail.jpg"
       backgroundsound=""
       backgroundsoundloops="0"
       titleid="pano44_title"
       descriptionid=""
       multires="true"
       planar="false"
       full360="true">

    <autorotate horizon="0.000000" tofov="90.000000" waittime="1" speed="16"/>

    <panoview h="-14.000000" v="0.000000" fov="90.000000" hmin="-180" hmax="180" vmin="-90" vmax="90" fovmax="90" />
    <view fisheye="0"
          limitview="range"
          hlookatmin="-180"
          hlookatmax="180"
          vlookatmin="-90"
          vlookatmax="90"
          maxpixelzoom="1.0"
          fovmax="90"
          fov="90.000000"
          hlookat="-14.000000"
          vlookat="0.000000"/>

    <preview url="%FIRSTXML%/_1_44/preview.jpg" type="CUBESTRIP" striporder="FRBLUD"/>

    <image type="CUBE" multires="true" baseindex="0" tilesize="512">
      <level tiledimagewidth="2547" tiledimageheight="2547">
        <front url="_1_44/0/2/%v_%u.jpg"/>
        <right url="_1_44/1/2/%v_%u.jpg"/>
        <back  url="_1_44/2/2/%v_%u.jpg"/>
        <left  url="_1_44/3/2/%v_%u.jpg"/>
        <up    url="_1_44/4/2/%v_%u.jpg"/>
        <down  url="_1_44/5/2/%v_%u.jpg"/>
      </level>
      <level tiledimagewidth="1273" tiledimageheight="1273">
        <front url="_1_44/0/1/%v_%u.jpg"/>
        <right url="_1_44/1/1/%v_%u.jpg"/>
        <back  url="_1_44/2/1/%v_%u.jpg"/>
        <left  url="_1_44/3/1/%v_%u.jpg"/>
        <up    url="_1_44/4/1/%v_%u.jpg"/>
        <down  url="_1_44/5/1/%v_%u.jpg"/>
      </level>
      <level tiledimagewidth="636" tiledimageheight="636">
        <front url="_1_44/0/0/%v_%u.jpg"/>
        <right url="_1_44/1/0/%v_%u.jpg"/>
        <back  url="_1_44/2/0/%v_%u.jpg"/>
        <left  url="_1_44/3/0/%v_%u.jpg"/>
        <up    url="_1_44/4/0/%v_%u.jpg"/>
        <down  url="_1_44/5/0/%v_%u.jpg"/>
      </level>
    </image>


  <!-- **** 1 Lensflares **** -->
<lensflare name="LENS74" set="DEFAULT" visible="false" ath="-134.485922" atv="-43.261199"/>
  <action name="hidepanolensflares">
    set(lensflare[LENS74].visible, false);
  </action>
  <action name="showpanolensflares">
    set(lensflare[LENS74].visible, true);
  </action>

  <!-- **** 1 Point Spots **** -->

  <hotspot name="spotpoint73"
           ath="8.717394" atv="-5.706539"
           visible="true"
           style="IconDefaultPointSpotStyle1"
           descriptionid=""
           onclick="onclickspotpoint73"
           />
  <hotspot name="spotpoint73" devices="flash" zorder="3"/>
  <hotspot name="spotpoint73" devices="html5+desktop" zorder="3" zorder2="1"/>
  <hotspot name="spotpoint73" devices="tablet|mobile" zorder2="1"/>
  <action name="onclickspotpoint73">
        mainloadscene(pano50);
      lookat(get(panoview.h), get(panoview.v), get(panoview.fov));
    
  </action>
  <action name="hidepanopointspots">
    set(hotspot[spotpoint73].visible, false);
  </action>
  <action name="showpanopointspots">
    set(hotspot[spotpoint73].visible, true);
  </action>


  <action name="showpanospotsaction">
    if (tour_displayspots,
    showpanopointspots();
    );
  </action>
  <action name="hidepanospotsaction">
    hidepanopointspots();
  </action>

  <action name="setzorder2onstandardspots">
    if (device.html5,
      ifnot (device.desktop,


        tween(hotspot[spotpoint73].zorder2, %1, 0.5, default, copy(urlbckpspotpoint73, hotspot[spotpoint73].url); set(hotspot[spotpoint73].url, ""); copy(hotspot[spotpoint73].url, urlbckpspotpoint73););

      );
    );
  </action>  

</scene>
  <!-- Group Group 64 : 1 panoramas -->
  

<!-- **** @PanoName="2" @PanoFile="F:/ПАНОРАМА/ArtPicnic/ARTPICNIC2/HDR/ALL/B.jpg" **** -->
<scene name="pano50"
       heading="-97.4000000000002"
       thumburl="%FIRSTXML%/_2_50/thumbnail.jpg"
       backgroundsound=""
       backgroundsoundloops="0"
       titleid="pano50_title"
       descriptionid=""
       multires="true"
       planar="false"
       full360="true">

    <autorotate horizon="0.000000" tofov="90.000000" waittime="1" speed="16"/>

    <panoview h="96.000000" v="0.000000" fov="90.000000" hmin="-180" hmax="180" vmin="-90" vmax="90" fovmax="90" />
    <view fisheye="0"
          limitview="range"
          hlookatmin="-180"
          hlookatmax="180"
          vlookatmin="-90"
          vlookatmax="90"
          maxpixelzoom="1.0"
          fovmax="90"
          fov="90.000000"
          hlookat="96.000000"
          vlookat="0.000000"/>

    <preview url="%FIRSTXML%/_2_50/preview.jpg" type="CUBESTRIP" striporder="FRBLUD"/>

    <image type="CUBE" multires="true" baseindex="0" tilesize="512">
      <level tiledimagewidth="2547" tiledimageheight="2547">
        <front url="_2_50/0/2/%v_%u.jpg"/>
        <right url="_2_50/1/2/%v_%u.jpg"/>
        <back  url="_2_50/2/2/%v_%u.jpg"/>
        <left  url="_2_50/3/2/%v_%u.jpg"/>
        <up    url="_2_50/4/2/%v_%u.jpg"/>
        <down  url="_2_50/5/2/%v_%u.jpg"/>
      </level>
      <level tiledimagewidth="1273" tiledimageheight="1273">
        <front url="_2_50/0/1/%v_%u.jpg"/>
        <right url="_2_50/1/1/%v_%u.jpg"/>
        <back  url="_2_50/2/1/%v_%u.jpg"/>
        <left  url="_2_50/3/1/%v_%u.jpg"/>
        <up    url="_2_50/4/1/%v_%u.jpg"/>
        <down  url="_2_50/5/1/%v_%u.jpg"/>
      </level>
      <level tiledimagewidth="636" tiledimageheight="636">
        <front url="_2_50/0/0/%v_%u.jpg"/>
        <right url="_2_50/1/0/%v_%u.jpg"/>
        <back  url="_2_50/2/0/%v_%u.jpg"/>
        <left  url="_2_50/3/0/%v_%u.jpg"/>
        <up    url="_2_50/4/0/%v_%u.jpg"/>
        <down  url="_2_50/5/0/%v_%u.jpg"/>
      </level>
    </image>


  <!-- **** 4 Point Spots **** -->

  <hotspot name="spotpoint75"
           ath="97.739632" atv="-10.396081"
           visible="true"
           style="IconDefaultPointSpotStyle1"
           descriptionid=""
           onclick="onclickspotpoint75"
           />
  <hotspot name="spotpoint75" devices="flash" zorder="3"/>
  <hotspot name="spotpoint75" devices="html5+desktop" zorder="3" zorder2="1"/>
  <hotspot name="spotpoint75" devices="tablet|mobile" zorder2="1"/>
  <action name="onclickspotpoint75">
        mainloadscene(pano53);
      lookat(get(panoview.h), get(panoview.v), get(panoview.fov));
    
  </action>
  <hotspot name="spotpoint76"
           ath="73.857608" atv="-10.396081"
           visible="true"
           style="IconDefaultPointSpotStyle1"
           descriptionid=""
           onclick="onclickspotpoint76"
           />
  <hotspot name="spotpoint76" devices="flash" zorder="3"/>
  <hotspot name="spotpoint76" devices="html5+desktop" zorder="3" zorder2="1"/>
  <hotspot name="spotpoint76" devices="tablet|mobile" zorder2="1"/>
  <action name="onclickspotpoint76">
        mainloadscene(pano52);
      lookat(get(panoview.h), get(panoview.v), get(panoview.fov));
    
  </action>
  <hotspot name="spotpoint77"
           ath="144.029517" atv="-11.584080"
           visible="true"
           style="IconDefaultPointSpotStyle1"
           descriptionid=""
           onclick="onclickspotpoint77"
           />
  <hotspot name="spotpoint77" devices="flash" zorder="3"/>
  <hotspot name="spotpoint77" devices="html5+desktop" zorder="3" zorder2="1"/>
  <hotspot name="spotpoint77" devices="tablet|mobile" zorder2="1"/>
  <action name="onclickspotpoint77">
        mainloadscene(pano51);
      lookat(get(panoview.h), get(panoview.v), get(panoview.fov));
    
  </action>
  <hotspot name="spotpoint78"
           ath="-78.280195" atv="-7.722718"
           visible="true"
           style="IconDefaultPointSpotStyle1"
           descriptionid=""
           onclick="onclickspotpoint78"
           />
  <hotspot name="spotpoint78" devices="flash" zorder="3"/>
  <hotspot name="spotpoint78" devices="html5+desktop" zorder="3" zorder2="1"/>
  <hotspot name="spotpoint78" devices="tablet|mobile" zorder2="1"/>
  <action name="onclickspotpoint78">
        mainloadscene(pano44);
      lookat(get(panoview.h), get(panoview.v), get(panoview.fov));
    
  </action>
  <action name="hidepanopointspots">
    set(hotspot[spotpoint75].visible, false);
    set(hotspot[spotpoint76].visible, false);
    set(hotspot[spotpoint77].visible, false);
    set(hotspot[spotpoint78].visible, false);
  </action>
  <action name="showpanopointspots">
    set(hotspot[spotpoint75].visible, true);
    set(hotspot[spotpoint76].visible, true);
    set(hotspot[spotpoint77].visible, true);
    set(hotspot[spotpoint78].visible, true);
  </action>


  <action name="showpanospotsaction">
    if (tour_displayspots,
    showpanopointspots();
    );
  </action>
  <action name="hidepanospotsaction">
    hidepanopointspots();
  </action>

  <action name="setzorder2onstandardspots">
    if (device.html5,
      ifnot (device.desktop,


        tween(hotspot[spotpoint75].zorder2, %1, 0.5, default, copy(urlbckpspotpoint75, hotspot[spotpoint75].url); set(hotspot[spotpoint75].url, ""); copy(hotspot[spotpoint75].url, urlbckpspotpoint75););

        tween(hotspot[spotpoint76].zorder2, %1, 0.5, default, copy(urlbckpspotpoint76, hotspot[spotpoint76].url); set(hotspot[spotpoint76].url, ""); copy(hotspot[spotpoint76].url, urlbckpspotpoint76););

        tween(hotspot[spotpoint77].zorder2, %1, 0.5, default, copy(urlbckpspotpoint77, hotspot[spotpoint77].url); set(hotspot[spotpoint77].url, ""); copy(hotspot[spotpoint77].url, urlbckpspotpoint77););

        tween(hotspot[spotpoint78].zorder2, %1, 0.5, default, copy(urlbckpspotpoint78, hotspot[spotpoint78].url); set(hotspot[spotpoint78].url, ""); copy(hotspot[spotpoint78].url, urlbckpspotpoint78););

      );
    );
  </action>  

</scene>
  <!-- Group Group 65 : 1 panoramas -->
  

<!-- **** @PanoName="3" @PanoFile="F:/ПАНОРАМА/ArtPicnic/ARTPICNIC2/HDR/ALL/C.jpg" **** -->
<scene name="pano51"
       heading="85.6000000000004"
       thumburl="%FIRSTXML%/_3_51/thumbnail.jpg"
       backgroundsound=""
       backgroundsoundloops="0"
       titleid="pano51_title"
       descriptionid=""
       multires="true"
       planar="false"
       full360="true">

    <autorotate horizon="0.000000" tofov="90.000000" waittime="1" speed="16"/>

    <panoview h="0.000000" v="0.000000" fov="90.000000" hmin="-180" hmax="180" vmin="-90" vmax="90" fovmax="90" />
    <view fisheye="0"
          limitview="range"
          hlookatmin="-180"
          hlookatmax="180"
          vlookatmin="-90"
          vlookatmax="90"
          maxpixelzoom="1.0"
          fovmax="90"
          fov="90.000000"
          hlookat="0.000000"
          vlookat="0.000000"/>

    <preview url="%FIRSTXML%/_3_51/preview.jpg" type="CUBESTRIP" striporder="FRBLUD"/>

    <image type="CUBE" multires="true" baseindex="0" tilesize="512">
      <level tiledimagewidth="2547" tiledimageheight="2547">
        <front url="_3_51/0/2/%v_%u.jpg"/>
        <right url="_3_51/1/2/%v_%u.jpg"/>
        <back  url="_3_51/2/2/%v_%u.jpg"/>
        <left  url="_3_51/3/2/%v_%u.jpg"/>
        <up    url="_3_51/4/2/%v_%u.jpg"/>
        <down  url="_3_51/5/2/%v_%u.jpg"/>
      </level>
      <level tiledimagewidth="1273" tiledimageheight="1273">
        <front url="_3_51/0/1/%v_%u.jpg"/>
        <right url="_3_51/1/1/%v_%u.jpg"/>
        <back  url="_3_51/2/1/%v_%u.jpg"/>
        <left  url="_3_51/3/1/%v_%u.jpg"/>
        <up    url="_3_51/4/1/%v_%u.jpg"/>
        <down  url="_3_51/5/1/%v_%u.jpg"/>
      </level>
      <level tiledimagewidth="636" tiledimageheight="636">
        <front url="_3_51/0/0/%v_%u.jpg"/>
        <right url="_3_51/1/0/%v_%u.jpg"/>
        <back  url="_3_51/2/0/%v_%u.jpg"/>
        <left  url="_3_51/3/0/%v_%u.jpg"/>
        <up    url="_3_51/4/0/%v_%u.jpg"/>
        <down  url="_3_51/5/0/%v_%u.jpg"/>
      </level>
    </image>


  <!-- **** 4 Point Spots **** -->

  <hotspot name="spotpoint81"
           ath="-177.610619" atv="-6.017761"
           visible="true"
           style="IconDefaultPointSpotStyle1"
           descriptionid=""
           onclick="onclickspotpoint81"
           />
  <hotspot name="spotpoint81" devices="flash" zorder="3"/>
  <hotspot name="spotpoint81" devices="html5+desktop" zorder="3" zorder2="1"/>
  <hotspot name="spotpoint81" devices="tablet|mobile" zorder2="1"/>
  <action name="onclickspotpoint81">
        mainloadscene(pano52);
      lookat(get(panoview.h), get(panoview.v), get(panoview.fov));
    
  </action>
  <hotspot name="spotpoint82"
           ath="125.309887" atv="-6.285242"
           visible="true"
           style="IconDefaultPointSpotStyle1"
           descriptionid=""
           onclick="onclickspotpoint82"
           />
  <hotspot name="spotpoint82" devices="flash" zorder="3"/>
  <hotspot name="spotpoint82" devices="html5+desktop" zorder="3" zorder2="1"/>
  <hotspot name="spotpoint82" devices="tablet|mobile" zorder2="1"/>
  <action name="onclickspotpoint82">
        mainloadscene(pano50);
      lookat(get(panoview.h), get(panoview.v), get(panoview.fov));
    
  </action>
  <hotspot name="spotpoint83"
           ath="-70.354085" atv="-8.959860"
           visible="true"
           style="IconDefaultPointSpotStyle1"
           descriptionid=""
           onclick="onclickspotpoint83"
           />
  <hotspot name="spotpoint83" devices="flash" zorder="3"/>
  <hotspot name="spotpoint83" devices="html5+desktop" zorder="3" zorder2="1"/>
  <hotspot name="spotpoint83" devices="tablet|mobile" zorder2="1"/>
  <action name="onclickspotpoint83">
        mainloadscene(pano53);
      lookat(get(panoview.h), get(panoview.v), get(panoview.fov));
    
  </action>
  <hotspot name="spotpoint85"
           ath="0.265324" atv="-10.029783"
           visible="true"
           style="IconDefaultPointSpotStyle1"
           descriptionid=""
           onclick="onclickspotpoint85"
           />
  <hotspot name="spotpoint85" devices="flash" zorder="3"/>
  <hotspot name="spotpoint85" devices="html5+desktop" zorder="3" zorder2="1"/>
  <hotspot name="spotpoint85" devices="tablet|mobile" zorder2="1"/>
  <action name="onclickspotpoint85">
        mainloadscene(pano57);
      lookat(get(panoview.h), get(panoview.v), get(panoview.fov));
    
  </action>
  <action name="hidepanopointspots">
    set(hotspot[spotpoint81].visible, false);
    set(hotspot[spotpoint82].visible, false);
    set(hotspot[spotpoint83].visible, false);
    set(hotspot[spotpoint85].visible, false);
  </action>
  <action name="showpanopointspots">
    set(hotspot[spotpoint81].visible, true);
    set(hotspot[spotpoint82].visible, true);
    set(hotspot[spotpoint83].visible, true);
    set(hotspot[spotpoint85].visible, true);
  </action>


  <action name="showpanospotsaction">
    if (tour_displayspots,
    showpanopointspots();
    );
  </action>
  <action name="hidepanospotsaction">
    hidepanopointspots();
  </action>

  <action name="setzorder2onstandardspots">
    if (device.html5,
      ifnot (device.desktop,


        tween(hotspot[spotpoint81].zorder2, %1, 0.5, default, copy(urlbckpspotpoint81, hotspot[spotpoint81].url); set(hotspot[spotpoint81].url, ""); copy(hotspot[spotpoint81].url, urlbckpspotpoint81););

        tween(hotspot[spotpoint82].zorder2, %1, 0.5, default, copy(urlbckpspotpoint82, hotspot[spotpoint82].url); set(hotspot[spotpoint82].url, ""); copy(hotspot[spotpoint82].url, urlbckpspotpoint82););

        tween(hotspot[spotpoint83].zorder2, %1, 0.5, default, copy(urlbckpspotpoint83, hotspot[spotpoint83].url); set(hotspot[spotpoint83].url, ""); copy(hotspot[spotpoint83].url, urlbckpspotpoint83););

        tween(hotspot[spotpoint85].zorder2, %1, 0.5, default, copy(urlbckpspotpoint85, hotspot[spotpoint85].url); set(hotspot[spotpoint85].url, ""); copy(hotspot[spotpoint85].url, urlbckpspotpoint85););

      );
    );
  </action>  

</scene>
  <!-- Group Group 66 : 1 panoramas -->
  

<!-- **** @PanoName="4" @PanoFile="F:/ПАНОРАМА/ArtPicnic/ARTPICNIC2/HDR/ALL/D.jpg" **** -->
<scene name="pano52"
       heading="-18.5999999999995"
       thumburl="%FIRSTXML%/_4_52/thumbnail.jpg"
       backgroundsound=""
       backgroundsoundloops="0"
       titleid="pano52_title"
       descriptionid=""
       multires="true"
       planar="false"
       full360="true">

    <autorotate horizon="0.000000" tofov="90.000000" waittime="1" speed="16"/>

    <panoview h="-55.000000" v="0.000000" fov="90.000000" hmin="-180" hmax="180" vmin="-90" vmax="90" fovmax="90" />
    <view fisheye="0"
          limitview="range"
          hlookatmin="-180"
          hlookatmax="180"
          vlookatmin="-90"
          vlookatmax="90"
          maxpixelzoom="1.0"
          fovmax="90"
          fov="90.000000"
          hlookat="-55.000000"
          vlookat="0.000000"/>

    <preview url="%FIRSTXML%/_4_52/preview.jpg" type="CUBESTRIP" striporder="FRBLUD"/>

    <image type="CUBE" multires="true" baseindex="0" tilesize="512">
      <level tiledimagewidth="2547" tiledimageheight="2547">
        <front url="_4_52/0/2/%v_%u.jpg"/>
        <right url="_4_52/1/2/%v_%u.jpg"/>
        <back  url="_4_52/2/2/%v_%u.jpg"/>
        <left  url="_4_52/3/2/%v_%u.jpg"/>
        <up    url="_4_52/4/2/%v_%u.jpg"/>
        <down  url="_4_52/5/2/%v_%u.jpg"/>
      </level>
      <level tiledimagewidth="1273" tiledimageheight="1273">
        <front url="_4_52/0/1/%v_%u.jpg"/>
        <right url="_4_52/1/1/%v_%u.jpg"/>
        <back  url="_4_52/2/1/%v_%u.jpg"/>
        <left  url="_4_52/3/1/%v_%u.jpg"/>
        <up    url="_4_52/4/1/%v_%u.jpg"/>
        <down  url="_4_52/5/1/%v_%u.jpg"/>
      </level>
      <level tiledimagewidth="636" tiledimageheight="636">
        <front url="_4_52/0/0/%v_%u.jpg"/>
        <right url="_4_52/1/0/%v_%u.jpg"/>
        <back  url="_4_52/2/0/%v_%u.jpg"/>
        <left  url="_4_52/3/0/%v_%u.jpg"/>
        <up    url="_4_52/4/0/%v_%u.jpg"/>
        <down  url="_4_52/5/0/%v_%u.jpg"/>
      </level>
    </image>


  <!-- **** 2 Point Spots **** -->

  <hotspot name="spotpoint79"
           ath="93.206871" atv="-11.009159"
           visible="true"
           style="IconDefaultPointSpotStyle1"
           descriptionid=""
           onclick="onclickspotpoint79"
           />
  <hotspot name="spotpoint79" devices="flash" zorder="3"/>
  <hotspot name="spotpoint79" devices="html5+desktop" zorder="3" zorder2="1"/>
  <hotspot name="spotpoint79" devices="tablet|mobile" zorder2="1"/>
  <action name="onclickspotpoint79">
        mainloadscene(pano50);
      lookat(get(panoview.h), get(panoview.v), get(panoview.fov));
    
  </action>
  <hotspot name="spotpoint80"
           ath="-2.865962" atv="-11.559602"
           visible="true"
           style="IconDefaultPointSpotStyle1"
           descriptionid=""
           onclick="onclickspotpoint80"
           />
  <hotspot name="spotpoint80" devices="flash" zorder="3"/>
  <hotspot name="spotpoint80" devices="html5+desktop" zorder="3" zorder2="1"/>
  <hotspot name="spotpoint80" devices="tablet|mobile" zorder2="1"/>
  <action name="onclickspotpoint80">
        mainloadscene(pano53);
      lookat(get(panoview.h), get(panoview.v), get(panoview.fov));
    
  </action>
  <action name="hidepanopointspots">
    set(hotspot[spotpoint79].visible, false);
    set(hotspot[spotpoint80].visible, false);
  </action>
  <action name="showpanopointspots">
    set(hotspot[spotpoint79].visible, true);
    set(hotspot[spotpoint80].visible, true);
  </action>


  <action name="showpanospotsaction">
    if (tour_displayspots,
    showpanopointspots();
    );
  </action>
  <action name="hidepanospotsaction">
    hidepanopointspots();
  </action>

  <action name="setzorder2onstandardspots">
    if (device.html5,
      ifnot (device.desktop,


        tween(hotspot[spotpoint79].zorder2, %1, 0.5, default, copy(urlbckpspotpoint79, hotspot[spotpoint79].url); set(hotspot[spotpoint79].url, ""); copy(hotspot[spotpoint79].url, urlbckpspotpoint79););

        tween(hotspot[spotpoint80].zorder2, %1, 0.5, default, copy(urlbckpspotpoint80, hotspot[spotpoint80].url); set(hotspot[spotpoint80].url, ""); copy(hotspot[spotpoint80].url, urlbckpspotpoint80););

      );
    );
  </action>  

</scene>
  <!-- Group Group 67 : 1 panoramas -->
  

<!-- **** @PanoName="5" @PanoFile="F:/ПАНОРАМА/ArtPicnic/ARTPICNIC2/HDR/ALL/E.jpeg" **** -->
<scene name="pano53"
       heading="80.7999999999998"
       thumburl="%FIRSTXML%/_5_53/thumbnail.jpg"
       backgroundsound=""
       backgroundsoundloops="0"
       titleid="pano53_title"
       descriptionid=""
       multires="true"
       planar="false"
       full360="true">

    <autorotate horizon="0.000000" tofov="90.000000" waittime="1" speed="16"/>

    <panoview h="-58.000000" v="0.000000" fov="90.000000" hmin="-180" hmax="180" vmin="-90" vmax="90" fovmax="90" />
    <view fisheye="0"
          limitview="range"
          hlookatmin="-180"
          hlookatmax="180"
          vlookatmin="-90"
          vlookatmax="90"
          maxpixelzoom="1.0"
          fovmax="90"
          fov="90.000000"
          hlookat="-58.000000"
          vlookat="0.000000"/>

    <preview url="%FIRSTXML%/_5_53/preview.jpg" type="CUBESTRIP" striporder="FRBLUD"/>

    <image type="CUBE" multires="true" baseindex="0" tilesize="512">
      <level tiledimagewidth="2547" tiledimageheight="2547">
        <front url="_5_53/0/2/%v_%u.jpg"/>
        <right url="_5_53/1/2/%v_%u.jpg"/>
        <back  url="_5_53/2/2/%v_%u.jpg"/>
        <left  url="_5_53/3/2/%v_%u.jpg"/>
        <up    url="_5_53/4/2/%v_%u.jpg"/>
        <down  url="_5_53/5/2/%v_%u.jpg"/>
      </level>
      <level tiledimagewidth="1273" tiledimageheight="1273">
        <front url="_5_53/0/1/%v_%u.jpg"/>
        <right url="_5_53/1/1/%v_%u.jpg"/>
        <back  url="_5_53/2/1/%v_%u.jpg"/>
        <left  url="_5_53/3/1/%v_%u.jpg"/>
        <up    url="_5_53/4/1/%v_%u.jpg"/>
        <down  url="_5_53/5/1/%v_%u.jpg"/>
      </level>
      <level tiledimagewidth="636" tiledimageheight="636">
        <front url="_5_53/0/0/%v_%u.jpg"/>
        <right url="_5_53/1/0/%v_%u.jpg"/>
        <back  url="_5_53/2/0/%v_%u.jpg"/>
        <left  url="_5_53/3/0/%v_%u.jpg"/>
        <up    url="_5_53/4/0/%v_%u.jpg"/>
        <down  url="_5_53/5/0/%v_%u.jpg"/>
      </level>
    </image>


  <!-- **** 4 Point Spots **** -->

  <hotspot name="spotpoint86"
           ath="-82.198076" atv="-6.694198"
           visible="true"
           style="IconDefaultPointSpotStyle1"
           descriptionid=""
           onclick="onclickspotpoint86"
           />
  <hotspot name="spotpoint86" devices="flash" zorder="3"/>
  <hotspot name="spotpoint86" devices="html5+desktop" zorder="3" zorder2="1"/>
  <hotspot name="spotpoint86" devices="tablet|mobile" zorder2="1"/>
  <action name="onclickspotpoint86">
        mainloadscene(pano54);
      lookat(get(panoview.h), get(panoview.v), get(panoview.fov));
    
  </action>
  <hotspot name="spotpoint87"
           ath="99.890635" atv="-2.479321"
           visible="true"
           style="IconDefaultPointSpotStyle1"
           descriptionid=""
           onclick="onclickspotpoint87"
           />
  <hotspot name="spotpoint87" devices="flash" zorder="3"/>
  <hotspot name="spotpoint87" devices="html5+desktop" zorder="3" zorder2="1"/>
  <hotspot name="spotpoint87" devices="tablet|mobile" zorder2="1"/>
  <action name="onclickspotpoint87">
        mainloadscene(pano50);
      lookat(get(panoview.h), get(panoview.v), get(panoview.fov));
    
  </action>
  <hotspot name="spotpoint88"
           ath="125.692928" atv="-3.471122"
           visible="true"
           style="IconDefaultPointSpotStyle1"
           descriptionid=""
           onclick="onclickspotpoint88"
           />
  <hotspot name="spotpoint88" devices="flash" zorder="3"/>
  <hotspot name="spotpoint88" devices="html5+desktop" zorder="3" zorder2="1"/>
  <hotspot name="spotpoint88" devices="tablet|mobile" zorder2="1"/>
  <action name="onclickspotpoint88">
        mainloadscene(pano52);
      lookat(get(panoview.h), get(panoview.v), get(panoview.fov));
    
  </action>
  <hotspot name="spotpoint89"
           ath="-4.791960" atv="-5.702398"
           visible="true"
           style="IconDefaultPointSpotStyle1"
           descriptionid=""
           onclick="onclickspotpoint89"
           />
  <hotspot name="spotpoint89" devices="flash" zorder="3"/>
  <hotspot name="spotpoint89" devices="html5+desktop" zorder="3" zorder2="1"/>
  <hotspot name="spotpoint89" devices="tablet|mobile" zorder2="1"/>
  <action name="onclickspotpoint89">
        mainloadscene(pano56);
      lookat(get(panoview.h), get(panoview.v), get(panoview.fov));
    
  </action>
  <action name="hidepanopointspots">
    set(hotspot[spotpoint86].visible, false);
    set(hotspot[spotpoint87].visible, false);
    set(hotspot[spotpoint88].visible, false);
    set(hotspot[spotpoint89].visible, false);
  </action>
  <action name="showpanopointspots">
    set(hotspot[spotpoint86].visible, true);
    set(hotspot[spotpoint87].visible, true);
    set(hotspot[spotpoint88].visible, true);
    set(hotspot[spotpoint89].visible, true);
  </action>


  <action name="showpanospotsaction">
    if (tour_displayspots,
    showpanopointspots();
    );
  </action>
  <action name="hidepanospotsaction">
    hidepanopointspots();
  </action>

  <action name="setzorder2onstandardspots">
    if (device.html5,
      ifnot (device.desktop,


        tween(hotspot[spotpoint86].zorder2, %1, 0.5, default, copy(urlbckpspotpoint86, hotspot[spotpoint86].url); set(hotspot[spotpoint86].url, ""); copy(hotspot[spotpoint86].url, urlbckpspotpoint86););

        tween(hotspot[spotpoint87].zorder2, %1, 0.5, default, copy(urlbckpspotpoint87, hotspot[spotpoint87].url); set(hotspot[spotpoint87].url, ""); copy(hotspot[spotpoint87].url, urlbckpspotpoint87););

        tween(hotspot[spotpoint88].zorder2, %1, 0.5, default, copy(urlbckpspotpoint88, hotspot[spotpoint88].url); set(hotspot[spotpoint88].url, ""); copy(hotspot[spotpoint88].url, urlbckpspotpoint88););

        tween(hotspot[spotpoint89].zorder2, %1, 0.5, default, copy(urlbckpspotpoint89, hotspot[spotpoint89].url); set(hotspot[spotpoint89].url, ""); copy(hotspot[spotpoint89].url, urlbckpspotpoint89););

      );
    );
  </action>  

</scene>
  <!-- Group Group 68 : 1 panoramas -->
  

<!-- **** @PanoName="6" @PanoFile="F:/ПАНОРАМА/ArtPicnic/ARTPICNIC2/HDR/ALL/F.jpeg" **** -->
<scene name="pano54"
       heading="153.2"
       thumburl="%FIRSTXML%/_6_54/thumbnail.jpg"
       backgroundsound=""
       backgroundsoundloops="0"
       titleid="pano54_title"
       descriptionid=""
       multires="true"
       planar="false"
       full360="true">

    <autorotate horizon="0.000000" tofov="90.000000" waittime="1" speed="16"/>

    <panoview h="-144.000000" v="0.000000" fov="90.000000" hmin="-180" hmax="180" vmin="-90" vmax="90" fovmax="90" />
    <view fisheye="0"
          limitview="range"
          hlookatmin="-180"
          hlookatmax="180"
          vlookatmin="-90"
          vlookatmax="90"
          maxpixelzoom="1.0"
          fovmax="90"
          fov="90.000000"
          hlookat="-144.000000"
          vlookat="0.000000"/>

    <preview url="%FIRSTXML%/_6_54/preview.jpg" type="CUBESTRIP" striporder="FRBLUD"/>

    <image type="CUBE" multires="true" baseindex="0" tilesize="512">
      <level tiledimagewidth="2547" tiledimageheight="2547">
        <front url="_6_54/0/2/%v_%u.jpg"/>
        <right url="_6_54/1/2/%v_%u.jpg"/>
        <back  url="_6_54/2/2/%v_%u.jpg"/>
        <left  url="_6_54/3/2/%v_%u.jpg"/>
        <up    url="_6_54/4/2/%v_%u.jpg"/>
        <down  url="_6_54/5/2/%v_%u.jpg"/>
      </level>
      <level tiledimagewidth="1273" tiledimageheight="1273">
        <front url="_6_54/0/1/%v_%u.jpg"/>
        <right url="_6_54/1/1/%v_%u.jpg"/>
        <back  url="_6_54/2/1/%v_%u.jpg"/>
        <left  url="_6_54/3/1/%v_%u.jpg"/>
        <up    url="_6_54/4/1/%v_%u.jpg"/>
        <down  url="_6_54/5/1/%v_%u.jpg"/>
      </level>
      <level tiledimagewidth="636" tiledimageheight="636">
        <front url="_6_54/0/0/%v_%u.jpg"/>
        <right url="_6_54/1/0/%v_%u.jpg"/>
        <back  url="_6_54/2/0/%v_%u.jpg"/>
        <left  url="_6_54/3/0/%v_%u.jpg"/>
        <up    url="_6_54/4/0/%v_%u.jpg"/>
        <down  url="_6_54/5/0/%v_%u.jpg"/>
      </level>
    </image>


  <!-- **** 3 Point Spots **** -->

  <hotspot name="spotpoint96"
           ath="13.884122" atv="-10.413178"
           visible="true"
           style="IconDefaultPointSpotStyle1"
           descriptionid=""
           onclick="onclickspotpoint96"
           />
  <hotspot name="spotpoint96" devices="flash" zorder="3"/>
  <hotspot name="spotpoint96" devices="html5+desktop" zorder="3" zorder2="1"/>
  <hotspot name="spotpoint96" devices="tablet|mobile" zorder2="1"/>
  <action name="onclickspotpoint96">
        mainloadscene(pano55);
      lookat(get(panoview.h), get(panoview.v), get(panoview.fov));
    
  </action>
  <hotspot name="spotpoint98"
           ath="122.498288" atv="-5.950438"
           visible="true"
           style="IconDefaultPointSpotStyle1"
           descriptionid=""
           onclick="onclickspotpoint98"
           />
  <hotspot name="spotpoint98" devices="flash" zorder="3"/>
  <hotspot name="spotpoint98" devices="html5+desktop" zorder="3" zorder2="1"/>
  <hotspot name="spotpoint98" devices="tablet|mobile" zorder2="1"/>
  <action name="onclickspotpoint98">
        mainloadscene(pano44);
      lookat(get(panoview.h), get(panoview.v), get(panoview.fov));
    
  </action>
  <hotspot name="spotpoint109"
           ath="-98.106118" atv="-13.813918"
           visible="true"
           style="IconDefaultPointSpotStyle1"
           descriptionid=""
           onclick="onclickspotpoint109"
           />
  <hotspot name="spotpoint109" devices="flash" zorder="3"/>
  <hotspot name="spotpoint109" devices="html5+desktop" zorder="3" zorder2="1"/>
  <hotspot name="spotpoint109" devices="tablet|mobile" zorder2="1"/>
  <action name="onclickspotpoint109">
        mainloadscene(pano45);
      lookat(get(panoview.h), get(panoview.v), get(panoview.fov));
    
  </action>
  <action name="hidepanopointspots">
    set(hotspot[spotpoint96].visible, false);
    set(hotspot[spotpoint98].visible, false);
    set(hotspot[spotpoint109].visible, false);
  </action>
  <action name="showpanopointspots">
    set(hotspot[spotpoint96].visible, true);
    set(hotspot[spotpoint98].visible, true);
    set(hotspot[spotpoint109].visible, true);
  </action>


  <action name="showpanospotsaction">
    if (tour_displayspots,
    showpanopointspots();
    );
  </action>
  <action name="hidepanospotsaction">
    hidepanopointspots();
  </action>

  <action name="setzorder2onstandardspots">
    if (device.html5,
      ifnot (device.desktop,


        tween(hotspot[spotpoint96].zorder2, %1, 0.5, default, copy(urlbckpspotpoint96, hotspot[spotpoint96].url); set(hotspot[spotpoint96].url, ""); copy(hotspot[spotpoint96].url, urlbckpspotpoint96););

        tween(hotspot[spotpoint98].zorder2, %1, 0.5, default, copy(urlbckpspotpoint98, hotspot[spotpoint98].url); set(hotspot[spotpoint98].url, ""); copy(hotspot[spotpoint98].url, urlbckpspotpoint98););

        tween(hotspot[spotpoint109].zorder2, %1, 0.5, default, copy(urlbckpspotpoint109, hotspot[spotpoint109].url); set(hotspot[spotpoint109].url, ""); copy(hotspot[spotpoint109].url, urlbckpspotpoint109););

      );
    );
  </action>  

</scene>
  <!-- Group Group 69 : 1 panoramas -->
  

<!-- **** @PanoName="7" @PanoFile="F:/ПАНОРАМА/ArtPicnic/ARTPICNIC2/HDR/ALL/G.jpg" **** -->
<scene name="pano55"
       heading="122.2"
       thumburl="%FIRSTXML%/_7_55/thumbnail.jpg"
       backgroundsound=""
       backgroundsoundloops="0"
       titleid="pano55_title"
       descriptionid=""
       multires="true"
       planar="false"
       full360="true">

    <autorotate horizon="0.000000" tofov="90.000000" waittime="1" speed="16"/>

    <panoview h="0.000000" v="0.000000" fov="90.000000" hmin="-180" hmax="180" vmin="-90" vmax="90" fovmax="90" />
    <view fisheye="0"
          limitview="range"
          hlookatmin="-180"
          hlookatmax="180"
          vlookatmin="-90"
          vlookatmax="90"
          maxpixelzoom="1.0"
          fovmax="90"
          fov="90.000000"
          hlookat="0.000000"
          vlookat="0.000000"/>

    <preview url="%FIRSTXML%/_7_55/preview.jpg" type="CUBESTRIP" striporder="FRBLUD"/>

    <image type="CUBE" multires="true" baseindex="0" tilesize="512">
      <level tiledimagewidth="2547" tiledimageheight="2547">
        <front url="_7_55/0/2/%v_%u.jpg"/>
        <right url="_7_55/1/2/%v_%u.jpg"/>
        <back  url="_7_55/2/2/%v_%u.jpg"/>
        <left  url="_7_55/3/2/%v_%u.jpg"/>
        <up    url="_7_55/4/2/%v_%u.jpg"/>
        <down  url="_7_55/5/2/%v_%u.jpg"/>
      </level>
      <level tiledimagewidth="1273" tiledimageheight="1273">
        <front url="_7_55/0/1/%v_%u.jpg"/>
        <right url="_7_55/1/1/%v_%u.jpg"/>
        <back  url="_7_55/2/1/%v_%u.jpg"/>
        <left  url="_7_55/3/1/%v_%u.jpg"/>
        <up    url="_7_55/4/1/%v_%u.jpg"/>
        <down  url="_7_55/5/1/%v_%u.jpg"/>
      </level>
      <level tiledimagewidth="636" tiledimageheight="636">
        <front url="_7_55/0/0/%v_%u.jpg"/>
        <right url="_7_55/1/0/%v_%u.jpg"/>
        <back  url="_7_55/2/0/%v_%u.jpg"/>
        <left  url="_7_55/3/0/%v_%u.jpg"/>
        <up    url="_7_55/4/0/%v_%u.jpg"/>
        <down  url="_7_55/5/0/%v_%u.jpg"/>
      </level>
    </image>


  <!-- **** 1 Point Spots **** -->

  <hotspot name="spotpoint99"
           ath="-13.799515" atv="-8.404021"
           visible="true"
           style="IconDefaultPointSpotStyle1"
           descriptionid=""
           onclick="onclickspotpoint99"
           />
  <hotspot name="spotpoint99" devices="flash" zorder="3"/>
  <hotspot name="spotpoint99" devices="html5+desktop" zorder="3" zorder2="1"/>
  <hotspot name="spotpoint99" devices="tablet|mobile" zorder2="1"/>
  <action name="onclickspotpoint99">
        mainloadscene(pano54);
      lookat(get(panoview.h), get(panoview.v), get(panoview.fov));
    
  </action>
  <action name="hidepanopointspots">
    set(hotspot[spotpoint99].visible, false);
  </action>
  <action name="showpanopointspots">
    set(hotspot[spotpoint99].visible, true);
  </action>


  <action name="showpanospotsaction">
    if (tour_displayspots,
    showpanopointspots();
    );
  </action>
  <action name="hidepanospotsaction">
    hidepanopointspots();
  </action>

  <action name="setzorder2onstandardspots">
    if (device.html5,
      ifnot (device.desktop,


        tween(hotspot[spotpoint99].zorder2, %1, 0.5, default, copy(urlbckpspotpoint99, hotspot[spotpoint99].url); set(hotspot[spotpoint99].url, ""); copy(hotspot[spotpoint99].url, urlbckpspotpoint99););

      );
    );
  </action>  

</scene>
  <!-- Group Group 70 : 1 panoramas -->
  

<!-- **** @PanoName="8" @PanoFile="F:/ПАНОРАМА/ArtPicnic/ARTPICNIC2/HDR/ALL/H.jpg" **** -->
<scene name="pano56"
       heading="-82.6"
       thumburl="%FIRSTXML%/_8_56/thumbnail.jpg"
       backgroundsound=""
       backgroundsoundloops="0"
       titleid="pano56_title"
       descriptionid=""
       multires="true"
       planar="false"
       full360="true">

    <autorotate horizon="0.000000" tofov="90.000000" waittime="1" speed="16"/>

    <panoview h="0.000000" v="0.000000" fov="90.000000" hmin="-180" hmax="180" vmin="-90" vmax="90" fovmax="90" />
    <view fisheye="0"
          limitview="range"
          hlookatmin="-180"
          hlookatmax="180"
          vlookatmin="-90"
          vlookatmax="90"
          maxpixelzoom="1.0"
          fovmax="90"
          fov="90.000000"
          hlookat="0.000000"
          vlookat="0.000000"/>

    <preview url="%FIRSTXML%/_8_56/preview.jpg" type="CUBESTRIP" striporder="FRBLUD"/>

    <image type="CUBE" multires="true" baseindex="0" tilesize="512">
      <level tiledimagewidth="2547" tiledimageheight="2547">
        <front url="_8_56/0/2/%v_%u.jpg"/>
        <right url="_8_56/1/2/%v_%u.jpg"/>
        <back  url="_8_56/2/2/%v_%u.jpg"/>
        <left  url="_8_56/3/2/%v_%u.jpg"/>
        <up    url="_8_56/4/2/%v_%u.jpg"/>
        <down  url="_8_56/5/2/%v_%u.jpg"/>
      </level>
      <level tiledimagewidth="1273" tiledimageheight="1273">
        <front url="_8_56/0/1/%v_%u.jpg"/>
        <right url="_8_56/1/1/%v_%u.jpg"/>
        <back  url="_8_56/2/1/%v_%u.jpg"/>
        <left  url="_8_56/3/1/%v_%u.jpg"/>
        <up    url="_8_56/4/1/%v_%u.jpg"/>
        <down  url="_8_56/5/1/%v_%u.jpg"/>
      </level>
      <level tiledimagewidth="636" tiledimageheight="636">
        <front url="_8_56/0/0/%v_%u.jpg"/>
        <right url="_8_56/1/0/%v_%u.jpg"/>
        <back  url="_8_56/2/0/%v_%u.jpg"/>
        <left  url="_8_56/3/0/%v_%u.jpg"/>
        <up    url="_8_56/4/0/%v_%u.jpg"/>
        <down  url="_8_56/5/0/%v_%u.jpg"/>
      </level>
    </image>


  <!-- **** 3 Point Spots **** -->

  <hotspot name="spotpoint93"
           ath="-48.070797" atv="-5.653619"
           visible="true"
           style="IconDefaultPointSpotStyle1"
           descriptionid=""
           onclick="onclickspotpoint93"
           />
  <hotspot name="spotpoint93" devices="flash" zorder="3"/>
  <hotspot name="spotpoint93" devices="html5+desktop" zorder="3" zorder2="1"/>
  <hotspot name="spotpoint93" devices="tablet|mobile" zorder2="1"/>
  <action name="onclickspotpoint93">
        mainloadscene(pano53);
      lookat(get(panoview.h), get(panoview.v), get(panoview.fov));
    
  </action>
  <hotspot name="spotpoint94"
           ath="144.819009" atv="-8.098560"
           visible="true"
           style="IconDefaultPointSpotStyle1"
           descriptionid=""
           onclick="onclickspotpoint94"
           />
  <hotspot name="spotpoint94" devices="flash" zorder="3"/>
  <hotspot name="spotpoint94" devices="html5+desktop" zorder="3" zorder2="1"/>
  <hotspot name="spotpoint94" devices="tablet|mobile" zorder2="1"/>
  <action name="onclickspotpoint94">
        mainloadscene(pano45);
      lookat(get(panoview.h), get(panoview.v), get(panoview.fov));
    
  </action>
  <hotspot name="spotpoint95"
           ath="-123.892200" atv="-3.819959"
           visible="true"
           style="IconDefaultPointSpotStyle1"
           descriptionid=""
           onclick="onclickspotpoint95"
           />
  <hotspot name="spotpoint95" devices="flash" zorder="3"/>
  <hotspot name="spotpoint95" devices="html5+desktop" zorder="3" zorder2="1"/>
  <hotspot name="spotpoint95" devices="tablet|mobile" zorder2="1"/>
  <action name="onclickspotpoint95">
        mainloadscene(pano57);
      lookat(get(panoview.h), get(panoview.v), get(panoview.fov));
    
  </action>
  <action name="hidepanopointspots">
    set(hotspot[spotpoint93].visible, false);
    set(hotspot[spotpoint94].visible, false);
    set(hotspot[spotpoint95].visible, false);
  </action>
  <action name="showpanopointspots">
    set(hotspot[spotpoint93].visible, true);
    set(hotspot[spotpoint94].visible, true);
    set(hotspot[spotpoint95].visible, true);
  </action>


  <action name="showpanospotsaction">
    if (tour_displayspots,
    showpanopointspots();
    );
  </action>
  <action name="hidepanospotsaction">
    hidepanopointspots();
  </action>

  <action name="setzorder2onstandardspots">
    if (device.html5,
      ifnot (device.desktop,


        tween(hotspot[spotpoint93].zorder2, %1, 0.5, default, copy(urlbckpspotpoint93, hotspot[spotpoint93].url); set(hotspot[spotpoint93].url, ""); copy(hotspot[spotpoint93].url, urlbckpspotpoint93););

        tween(hotspot[spotpoint94].zorder2, %1, 0.5, default, copy(urlbckpspotpoint94, hotspot[spotpoint94].url); set(hotspot[spotpoint94].url, ""); copy(hotspot[spotpoint94].url, urlbckpspotpoint94););

        tween(hotspot[spotpoint95].zorder2, %1, 0.5, default, copy(urlbckpspotpoint95, hotspot[spotpoint95].url); set(hotspot[spotpoint95].url, ""); copy(hotspot[spotpoint95].url, urlbckpspotpoint95););

      );
    );
  </action>  

</scene>
  <!-- Group Group 59 : 1 panoramas -->
  

<!-- **** @PanoName="10" @PanoFile="F:/ПАНОРАМА/ArtPicnic/ARTPICNIC2/HDR/ALL/I.jpeg" **** -->
<scene name="pano45"
       heading="0"
       thumburl="%FIRSTXML%/_10_45/thumbnail.jpg"
       backgroundsound=""
       backgroundsoundloops="0"
       titleid="pano45_title"
       descriptionid=""
       multires="true"
       planar="false"
       full360="true">

    <autorotate horizon="0.000000" tofov="90.000000" waittime="1" speed="16"/>

    <panoview h="-71.000000" v="0.000000" fov="90.000000" hmin="-180" hmax="180" vmin="-90" vmax="90" fovmax="90" />
    <view fisheye="0"
          limitview="range"
          hlookatmin="-180"
          hlookatmax="180"
          vlookatmin="-90"
          vlookatmax="90"
          maxpixelzoom="1.0"
          fovmax="90"
          fov="90.000000"
          hlookat="-71.000000"
          vlookat="0.000000"/>

    <preview url="%FIRSTXML%/_10_45/preview.jpg" type="CUBESTRIP" striporder="FRBLUD"/>

    <image type="CUBE" multires="true" baseindex="0" tilesize="512">
      <level tiledimagewidth="2546" tiledimageheight="2546">
        <front url="_10_45/0/2/%v_%u.jpg"/>
        <right url="_10_45/1/2/%v_%u.jpg"/>
        <back  url="_10_45/2/2/%v_%u.jpg"/>
        <left  url="_10_45/3/2/%v_%u.jpg"/>
        <up    url="_10_45/4/2/%v_%u.jpg"/>
        <down  url="_10_45/5/2/%v_%u.jpg"/>
      </level>
      <level tiledimagewidth="1273" tiledimageheight="1273">
        <front url="_10_45/0/1/%v_%u.jpg"/>
        <right url="_10_45/1/1/%v_%u.jpg"/>
        <back  url="_10_45/2/1/%v_%u.jpg"/>
        <left  url="_10_45/3/1/%v_%u.jpg"/>
        <up    url="_10_45/4/1/%v_%u.jpg"/>
        <down  url="_10_45/5/1/%v_%u.jpg"/>
      </level>
      <level tiledimagewidth="636" tiledimageheight="636">
        <front url="_10_45/0/0/%v_%u.jpg"/>
        <right url="_10_45/1/0/%v_%u.jpg"/>
        <back  url="_10_45/2/0/%v_%u.jpg"/>
        <left  url="_10_45/3/0/%v_%u.jpg"/>
        <up    url="_10_45/4/0/%v_%u.jpg"/>
        <down  url="_10_45/5/0/%v_%u.jpg"/>
      </level>
    </image>


  <!-- **** 2 Point Spots **** -->

  <hotspot name="spotpoint100"
           ath="122.367246" atv="-9.234357"
           visible="true"
           style="IconDefaultPointSpotStyle1"
           descriptionid=""
           onclick="onclickspotpoint100"
           />
  <hotspot name="spotpoint100" devices="flash" zorder="3"/>
  <hotspot name="spotpoint100" devices="html5+desktop" zorder="3" zorder2="1"/>
  <hotspot name="spotpoint100" devices="tablet|mobile" zorder2="1"/>
  <action name="onclickspotpoint100">
        mainloadscene(pano46);
      lookat(get(panoview.h), get(panoview.v), get(panoview.fov));
    
  </action>
  <hotspot name="spotpoint125"
           ath="-75.393355" atv="-4.046043"
           visible="true"
           style="IconDefaultPointSpotStyle1"
           descriptionid=""
           onclick="onclickspotpoint125"
           />
  <hotspot name="spotpoint125" devices="flash" zorder="3"/>
  <hotspot name="spotpoint125" devices="html5+desktop" zorder="3" zorder2="1"/>
  <hotspot name="spotpoint125" devices="tablet|mobile" zorder2="1"/>
  <action name="onclickspotpoint125">
        mainloadscene(pano54);
      lookat(get(panoview.h), get(panoview.v), get(panoview.fov));
    
  </action>
  <action name="hidepanopointspots">
    set(hotspot[spotpoint100].visible, false);
    set(hotspot[spotpoint125].visible, false);
  </action>
  <action name="showpanopointspots">
    set(hotspot[spotpoint100].visible, true);
    set(hotspot[spotpoint125].visible, true);
  </action>


  <action name="showpanospotsaction">
    if (tour_displayspots,
    showpanopointspots();
    );
  </action>
  <action name="hidepanospotsaction">
    hidepanopointspots();
  </action>

  <action name="setzorder2onstandardspots">
    if (device.html5,
      ifnot (device.desktop,


        tween(hotspot[spotpoint100].zorder2, %1, 0.5, default, copy(urlbckpspotpoint100, hotspot[spotpoint100].url); set(hotspot[spotpoint100].url, ""); copy(hotspot[spotpoint100].url, urlbckpspotpoint100););

        tween(hotspot[spotpoint125].zorder2, %1, 0.5, default, copy(urlbckpspotpoint125, hotspot[spotpoint125].url); set(hotspot[spotpoint125].url, ""); copy(hotspot[spotpoint125].url, urlbckpspotpoint125););

      );
    );
  </action>  

</scene>
  <!-- Group Group 60 : 1 panoramas -->
  

<!-- **** @PanoName="11" @PanoFile="F:/ПАНОРАМА/ArtPicnic/ARTPICNIC2/HDR/ALL/J.jpg" **** -->
<scene name="pano46"
       heading="0"
       thumburl="%FIRSTXML%/_11_46/thumbnail.jpg"
       backgroundsound=""
       backgroundsoundloops="0"
       titleid="pano46_title"
       descriptionid=""
       multires="true"
       planar="false"
       full360="true">

    <autorotate horizon="0.000000" tofov="90.000000" waittime="1" speed="16"/>

    <panoview h="0.000000" v="0.000000" fov="90.000000" hmin="-180" hmax="180" vmin="-90" vmax="90" fovmax="90" />
    <view fisheye="0"
          limitview="range"
          hlookatmin="-180"
          hlookatmax="180"
          vlookatmin="-90"
          vlookatmax="90"
          maxpixelzoom="1.0"
          fovmax="90"
          fov="90.000000"
          hlookat="0.000000"
          vlookat="0.000000"/>

    <preview url="%FIRSTXML%/_11_46/preview.jpg" type="CUBESTRIP" striporder="FRBLUD"/>

    <image type="CUBE" multires="true" baseindex="0" tilesize="512">
      <level tiledimagewidth="2547" tiledimageheight="2547">
        <front url="_11_46/0/2/%v_%u.jpg"/>
        <right url="_11_46/1/2/%v_%u.jpg"/>
        <back  url="_11_46/2/2/%v_%u.jpg"/>
        <left  url="_11_46/3/2/%v_%u.jpg"/>
        <up    url="_11_46/4/2/%v_%u.jpg"/>
        <down  url="_11_46/5/2/%v_%u.jpg"/>
      </level>
      <level tiledimagewidth="1273" tiledimageheight="1273">
        <front url="_11_46/0/1/%v_%u.jpg"/>
        <right url="_11_46/1/1/%v_%u.jpg"/>
        <back  url="_11_46/2/1/%v_%u.jpg"/>
        <left  url="_11_46/3/1/%v_%u.jpg"/>
        <up    url="_11_46/4/1/%v_%u.jpg"/>
        <down  url="_11_46/5/1/%v_%u.jpg"/>
      </level>
      <level tiledimagewidth="636" tiledimageheight="636">
        <front url="_11_46/0/0/%v_%u.jpg"/>
        <right url="_11_46/1/0/%v_%u.jpg"/>
        <back  url="_11_46/2/0/%v_%u.jpg"/>
        <left  url="_11_46/3/0/%v_%u.jpg"/>
        <up    url="_11_46/4/0/%v_%u.jpg"/>
        <down  url="_11_46/5/0/%v_%u.jpg"/>
      </level>
    </image>


  <!-- **** 2 Point Spots **** -->

  <hotspot name="spotpoint101"
           ath="3.040552" atv="-17.999999"
           visible="true"
           style="IconDefaultPointSpotStyle1"
           descriptionid=""
           onclick="onclickspotpoint101"
           />
  <hotspot name="spotpoint101" devices="flash" zorder="3"/>
  <hotspot name="spotpoint101" devices="html5+desktop" zorder="3" zorder2="1"/>
  <hotspot name="spotpoint101" devices="tablet|mobile" zorder2="1"/>
  <action name="onclickspotpoint101">
        mainloadscene(pano47);
      lookat(get(panoview.h), get(panoview.v), get(panoview.fov));
    
  </action>
  <hotspot name="spotpoint102"
           ath="-117.973080" atv="-4.769279"
           visible="true"
           style="IconDefaultPointSpotStyle1"
           descriptionid=""
           onclick="onclickspotpoint102"
           />
  <hotspot name="spotpoint102" devices="flash" zorder="3"/>
  <hotspot name="spotpoint102" devices="html5+desktop" zorder="3" zorder2="1"/>
  <hotspot name="spotpoint102" devices="tablet|mobile" zorder2="1"/>
  <action name="onclickspotpoint102">
        mainloadscene(pano57);
      lookat(get(panoview.h), get(panoview.v), get(panoview.fov));
    
  </action>
  <action name="hidepanopointspots">
    set(hotspot[spotpoint101].visible, false);
    set(hotspot[spotpoint102].visible, false);
  </action>
  <action name="showpanopointspots">
    set(hotspot[spotpoint101].visible, true);
    set(hotspot[spotpoint102].visible, true);
  </action>


  <action name="showpanospotsaction">
    if (tour_displayspots,
    showpanopointspots();
    );
  </action>
  <action name="hidepanospotsaction">
    hidepanopointspots();
  </action>

  <action name="setzorder2onstandardspots">
    if (device.html5,
      ifnot (device.desktop,


        tween(hotspot[spotpoint101].zorder2, %1, 0.5, default, copy(urlbckpspotpoint101, hotspot[spotpoint101].url); set(hotspot[spotpoint101].url, ""); copy(hotspot[spotpoint101].url, urlbckpspotpoint101););

        tween(hotspot[spotpoint102].zorder2, %1, 0.5, default, copy(urlbckpspotpoint102, hotspot[spotpoint102].url); set(hotspot[spotpoint102].url, ""); copy(hotspot[spotpoint102].url, urlbckpspotpoint102););

      );
    );
  </action>  

</scene>
  <!-- Group Group 61 : 1 panoramas -->
  

<!-- **** @PanoName="12" @PanoFile="F:/ПАНОРАМА/ArtPicnic/ARTPICNIC2/HDR/ALL/K.jpeg" **** -->
<scene name="pano47"
       heading="0"
       thumburl="%FIRSTXML%/_12_47/thumbnail.jpg"
       backgroundsound=""
       backgroundsoundloops="0"
       titleid="pano47_title"
       descriptionid=""
       multires="true"
       planar="false"
       full360="true">

    <autorotate horizon="0.000000" tofov="90.000000" waittime="1" speed="16"/>

    <panoview h="0.000000" v="0.000000" fov="90.000000" hmin="-180" hmax="180" vmin="-90" vmax="90" fovmax="90" />
    <view fisheye="0"
          limitview="range"
          hlookatmin="-180"
          hlookatmax="180"
          vlookatmin="-90"
          vlookatmax="90"
          maxpixelzoom="1.0"
          fovmax="90"
          fov="90.000000"
          hlookat="0.000000"
          vlookat="0.000000"/>

    <preview url="%FIRSTXML%/_12_47/preview.jpg" type="CUBESTRIP" striporder="FRBLUD"/>

    <image type="CUBE" multires="true" baseindex="0" tilesize="512">
      <level tiledimagewidth="2547" tiledimageheight="2547">
        <front url="_12_47/0/2/%v_%u.jpg"/>
        <right url="_12_47/1/2/%v_%u.jpg"/>
        <back  url="_12_47/2/2/%v_%u.jpg"/>
        <left  url="_12_47/3/2/%v_%u.jpg"/>
        <up    url="_12_47/4/2/%v_%u.jpg"/>
        <down  url="_12_47/5/2/%v_%u.jpg"/>
      </level>
      <level tiledimagewidth="1273" tiledimageheight="1273">
        <front url="_12_47/0/1/%v_%u.jpg"/>
        <right url="_12_47/1/1/%v_%u.jpg"/>
        <back  url="_12_47/2/1/%v_%u.jpg"/>
        <left  url="_12_47/3/1/%v_%u.jpg"/>
        <up    url="_12_47/4/1/%v_%u.jpg"/>
        <down  url="_12_47/5/1/%v_%u.jpg"/>
      </level>
      <level tiledimagewidth="636" tiledimageheight="636">
        <front url="_12_47/0/0/%v_%u.jpg"/>
        <right url="_12_47/1/0/%v_%u.jpg"/>
        <back  url="_12_47/2/0/%v_%u.jpg"/>
        <left  url="_12_47/3/0/%v_%u.jpg"/>
        <up    url="_12_47/4/0/%v_%u.jpg"/>
        <down  url="_12_47/5/0/%v_%u.jpg"/>
      </level>
    </image>


  <!-- **** 3 Point Spots **** -->

  <hotspot name="spotpoint103"
           ath="0.000000" atv="-7.735861"
           visible="true"
           style="IconDefaultPointSpotStyle1"
           descriptionid=""
           onclick="onclickspotpoint103"
           />
  <hotspot name="spotpoint103" devices="flash" zorder="3"/>
  <hotspot name="spotpoint103" devices="html5+desktop" zorder="3" zorder2="1"/>
  <hotspot name="spotpoint103" devices="tablet|mobile" zorder2="1"/>
  <action name="onclickspotpoint103">
        mainloadscene(pano48);
      lookat(get(panoview.h), get(panoview.v), get(panoview.fov));
    
  </action>
  <hotspot name="spotpoint104"
           ath="174.760916" atv="-7.358581"
           visible="true"
           style="IconDefaultPointSpotStyle1"
           descriptionid=""
           onclick="onclickspotpoint104"
           />
  <hotspot name="spotpoint104" devices="flash" zorder="3"/>
  <hotspot name="spotpoint104" devices="html5+desktop" zorder="3" zorder2="1"/>
  <hotspot name="spotpoint104" devices="tablet|mobile" zorder2="1"/>
  <action name="onclickspotpoint104">
        mainloadscene(pano46);
      lookat(get(panoview.h), get(panoview.v), get(panoview.fov));
    
  </action>
  <hotspot name="spotpoint105"
           ath="-107.946001" atv="-10.061283"
           visible="true"
           style="IconDefaultPointSpotStyle1"
           descriptionid=""
           onclick="onclickspotpoint105"
           />
  <hotspot name="spotpoint105" devices="flash" zorder="3"/>
  <hotspot name="spotpoint105" devices="html5+desktop" zorder="3" zorder2="1"/>
  <hotspot name="spotpoint105" devices="tablet|mobile" zorder2="1"/>
  <action name="onclickspotpoint105">
        mainloadscene(pano45);
      lookat(get(panoview.h), get(panoview.v), get(panoview.fov));
    
  </action>
  <action name="hidepanopointspots">
    set(hotspot[spotpoint103].visible, false);
    set(hotspot[spotpoint104].visible, false);
    set(hotspot[spotpoint105].visible, false);
  </action>
  <action name="showpanopointspots">
    set(hotspot[spotpoint103].visible, true);
    set(hotspot[spotpoint104].visible, true);
    set(hotspot[spotpoint105].visible, true);
  </action>


  <action name="showpanospotsaction">
    if (tour_displayspots,
    showpanopointspots();
    );
  </action>
  <action name="hidepanospotsaction">
    hidepanopointspots();
  </action>

  <action name="setzorder2onstandardspots">
    if (device.html5,
      ifnot (device.desktop,


        tween(hotspot[spotpoint103].zorder2, %1, 0.5, default, copy(urlbckpspotpoint103, hotspot[spotpoint103].url); set(hotspot[spotpoint103].url, ""); copy(hotspot[spotpoint103].url, urlbckpspotpoint103););

        tween(hotspot[spotpoint104].zorder2, %1, 0.5, default, copy(urlbckpspotpoint104, hotspot[spotpoint104].url); set(hotspot[spotpoint104].url, ""); copy(hotspot[spotpoint104].url, urlbckpspotpoint104););

        tween(hotspot[spotpoint105].zorder2, %1, 0.5, default, copy(urlbckpspotpoint105, hotspot[spotpoint105].url); set(hotspot[spotpoint105].url, ""); copy(hotspot[spotpoint105].url, urlbckpspotpoint105););

      );
    );
  </action>  

</scene>
  <!-- Group Group 62 : 1 panoramas -->
  

<!-- **** @PanoName="13" @PanoFile="F:/ПАНОРАМА/ArtPicnic/ARTPICNIC2/HDR/ALL/L.jpg" **** -->
<scene name="pano48"
       heading="0"
       thumburl="%FIRSTXML%/_13_48/thumbnail.jpg"
       backgroundsound=""
       backgroundsoundloops="0"
       titleid="pano48_title"
       descriptionid=""
       multires="true"
       planar="false"
       full360="true">

    <autorotate horizon="0.000000" tofov="90.000000" waittime="1" speed="16"/>

    <panoview h="0.000000" v="0.000000" fov="90.000000" hmin="-180" hmax="180" vmin="-90" vmax="90" fovmax="90" />
    <view fisheye="0"
          limitview="range"
          hlookatmin="-180"
          hlookatmax="180"
          vlookatmin="-90"
          vlookatmax="90"
          maxpixelzoom="1.0"
          fovmax="90"
          fov="90.000000"
          hlookat="0.000000"
          vlookat="0.000000"/>

    <preview url="%FIRSTXML%/_13_48/preview.jpg" type="CUBESTRIP" striporder="FRBLUD"/>

    <image type="CUBE" multires="true" baseindex="0" tilesize="512">
      <level tiledimagewidth="2547" tiledimageheight="2547">
        <front url="_13_48/0/2/%v_%u.jpg"/>
        <right url="_13_48/1/2/%v_%u.jpg"/>
        <back  url="_13_48/2/2/%v_%u.jpg"/>
        <left  url="_13_48/3/2/%v_%u.jpg"/>
        <up    url="_13_48/4/2/%v_%u.jpg"/>
        <down  url="_13_48/5/2/%v_%u.jpg"/>
      </level>
      <level tiledimagewidth="1273" tiledimageheight="1273">
        <front url="_13_48/0/1/%v_%u.jpg"/>
        <right url="_13_48/1/1/%v_%u.jpg"/>
        <back  url="_13_48/2/1/%v_%u.jpg"/>
        <left  url="_13_48/3/1/%v_%u.jpg"/>
        <up    url="_13_48/4/1/%v_%u.jpg"/>
        <down  url="_13_48/5/1/%v_%u.jpg"/>
      </level>
      <level tiledimagewidth="636" tiledimageheight="636">
        <front url="_13_48/0/0/%v_%u.jpg"/>
        <right url="_13_48/1/0/%v_%u.jpg"/>
        <back  url="_13_48/2/0/%v_%u.jpg"/>
        <left  url="_13_48/3/0/%v_%u.jpg"/>
        <up    url="_13_48/4/0/%v_%u.jpg"/>
        <down  url="_13_48/5/0/%v_%u.jpg"/>
      </level>
    </image>


  <!-- **** 2 Point Spots **** -->

  <hotspot name="spotpoint106"
           ath="168.516004" atv="-13.286880"
           visible="true"
           style="IconDefaultPointSpotStyle1"
           descriptionid=""
           onclick="onclickspotpoint106"
           />
  <hotspot name="spotpoint106" devices="flash" zorder="3"/>
  <hotspot name="spotpoint106" devices="html5+desktop" zorder="3" zorder2="1"/>
  <hotspot name="spotpoint106" devices="tablet|mobile" zorder2="1"/>
  <action name="onclickspotpoint106">
        mainloadscene(pano47);
      lookat(get(panoview.h), get(panoview.v), get(panoview.fov));
    
  </action>
  <hotspot name="spotpoint107"
           ath="4.244049" atv="-10.780018"
           visible="true"
           style="IconDefaultPointSpotStyle1"
           descriptionid=""
           onclick="onclickspotpoint107"
           />
  <hotspot name="spotpoint107" devices="flash" zorder="3"/>
  <hotspot name="spotpoint107" devices="html5+desktop" zorder="3" zorder2="1"/>
  <hotspot name="spotpoint107" devices="tablet|mobile" zorder2="1"/>
  <action name="onclickspotpoint107">
        mainloadscene(pano49);
      lookat(get(panoview.h), get(panoview.v), get(panoview.fov));
    
  </action>
  <action name="hidepanopointspots">
    set(hotspot[spotpoint106].visible, false);
    set(hotspot[spotpoint107].visible, false);
  </action>
  <action name="showpanopointspots">
    set(hotspot[spotpoint106].visible, true);
    set(hotspot[spotpoint107].visible, true);
  </action>


  <action name="showpanospotsaction">
    if (tour_displayspots,
    showpanopointspots();
    );
  </action>
  <action name="hidepanospotsaction">
    hidepanopointspots();
  </action>

  <action name="setzorder2onstandardspots">
    if (device.html5,
      ifnot (device.desktop,


        tween(hotspot[spotpoint106].zorder2, %1, 0.5, default, copy(urlbckpspotpoint106, hotspot[spotpoint106].url); set(hotspot[spotpoint106].url, ""); copy(hotspot[spotpoint106].url, urlbckpspotpoint106););

        tween(hotspot[spotpoint107].zorder2, %1, 0.5, default, copy(urlbckpspotpoint107, hotspot[spotpoint107].url); set(hotspot[spotpoint107].url, ""); copy(hotspot[spotpoint107].url, urlbckpspotpoint107););

      );
    );
  </action>  

</scene>
  <!-- Group Group 63 : 1 panoramas -->
  

<!-- **** @PanoName="14" @PanoFile="F:/ПАНОРАМА/ArtPicnic/ARTPICNIC2/HDR/ALL/M.jpg" **** -->
<scene name="pano49"
       heading="0"
       thumburl="%FIRSTXML%/_14_49/thumbnail.jpg"
       backgroundsound=""
       backgroundsoundloops="0"
       titleid="pano49_title"
       descriptionid=""
       multires="true"
       planar="false"
       full360="true">

    <autorotate horizon="0.000000" tofov="90.000000" waittime="1" speed="16"/>

    <panoview h="0.000000" v="0.000000" fov="90.000000" hmin="-180" hmax="180" vmin="-90" vmax="90" fovmax="90" />
    <view fisheye="0"
          limitview="range"
          hlookatmin="-180"
          hlookatmax="180"
          vlookatmin="-90"
          vlookatmax="90"
          maxpixelzoom="1.0"
          fovmax="90"
          fov="90.000000"
          hlookat="0.000000"
          vlookat="0.000000"/>

    <preview url="%FIRSTXML%/_14_49/preview.jpg" type="CUBESTRIP" striporder="FRBLUD"/>

    <image type="CUBE" multires="true" baseindex="0" tilesize="512">
      <level tiledimagewidth="2547" tiledimageheight="2547">
        <front url="_14_49/0/2/%v_%u.jpg"/>
        <right url="_14_49/1/2/%v_%u.jpg"/>
        <back  url="_14_49/2/2/%v_%u.jpg"/>
        <left  url="_14_49/3/2/%v_%u.jpg"/>
        <up    url="_14_49/4/2/%v_%u.jpg"/>
        <down  url="_14_49/5/2/%v_%u.jpg"/>
      </level>
      <level tiledimagewidth="1273" tiledimageheight="1273">
        <front url="_14_49/0/1/%v_%u.jpg"/>
        <right url="_14_49/1/1/%v_%u.jpg"/>
        <back  url="_14_49/2/1/%v_%u.jpg"/>
        <left  url="_14_49/3/1/%v_%u.jpg"/>
        <up    url="_14_49/4/1/%v_%u.jpg"/>
        <down  url="_14_49/5/1/%v_%u.jpg"/>
      </level>
      <level tiledimagewidth="636" tiledimageheight="636">
        <front url="_14_49/0/0/%v_%u.jpg"/>
        <right url="_14_49/1/0/%v_%u.jpg"/>
        <back  url="_14_49/2/0/%v_%u.jpg"/>
        <left  url="_14_49/3/0/%v_%u.jpg"/>
        <up    url="_14_49/4/0/%v_%u.jpg"/>
        <down  url="_14_49/5/0/%v_%u.jpg"/>
      </level>
    </image>


  <!-- **** 1 Point Spots **** -->

  <hotspot name="spotpoint108"
           ath="-148.458311" atv="6.264900"
           visible="true"
           style="IconDefaultPointSpotStyle1"
           descriptionid=""
           onclick="onclickspotpoint108"
           />
  <hotspot name="spotpoint108" devices="flash" zorder="3"/>
  <hotspot name="spotpoint108" devices="html5+desktop" zorder="3" zorder2="1"/>
  <hotspot name="spotpoint108" devices="tablet|mobile" zorder2="1"/>
  <action name="onclickspotpoint108">
        mainloadscene(pano48);
      lookat(get(panoview.h), get(panoview.v), get(panoview.fov));
    
  </action>
  <action name="hidepanopointspots">
    set(hotspot[spotpoint108].visible, false);
  </action>
  <action name="showpanopointspots">
    set(hotspot[spotpoint108].visible, true);
  </action>


  <action name="showpanospotsaction">
    if (tour_displayspots,
    showpanopointspots();
    );
  </action>
  <action name="hidepanospotsaction">
    hidepanopointspots();
  </action>

  <action name="setzorder2onstandardspots">
    if (device.html5,
      ifnot (device.desktop,


        tween(hotspot[spotpoint108].zorder2, %1, 0.5, default, copy(urlbckpspotpoint108, hotspot[spotpoint108].url); set(hotspot[spotpoint108].url, ""); copy(hotspot[spotpoint108].url, urlbckpspotpoint108););

      );
    );
  </action>  

</scene>
  <!-- Group Group 72 : 1 panoramas -->
  

<!-- **** @PanoName="9" @PanoFile="F:/ПАНОРАМА/ArtPicnic/ARTPICNIC2/HDR/ALL/N.jpg" **** -->
<scene name="pano57"
       heading="0"
       thumburl="%FIRSTXML%/_9_57/thumbnail.jpg"
       backgroundsound=""
       backgroundsoundloops="0"
       titleid="pano57_title"
       descriptionid=""
       multires="true"
       planar="false"
       full360="true">

    <autorotate horizon="0.000000" tofov="90.000000" waittime="1" speed="16"/>

    <panoview h="0.000000" v="0.000000" fov="90.000000" hmin="-180" hmax="180" vmin="-90" vmax="90" fovmax="90" />
    <view fisheye="0"
          limitview="range"
          hlookatmin="-180"
          hlookatmax="180"
          vlookatmin="-90"
          vlookatmax="90"
          maxpixelzoom="1.0"
          fovmax="90"
          fov="90.000000"
          hlookat="0.000000"
          vlookat="0.000000"/>

    <preview url="%FIRSTXML%/_9_57/preview.jpg" type="CUBESTRIP" striporder="FRBLUD"/>

    <image type="CUBE" multires="true" baseindex="0" tilesize="512">
      <level tiledimagewidth="2547" tiledimageheight="2547">
        <front url="_9_57/0/2/%v_%u.jpg"/>
        <right url="_9_57/1/2/%v_%u.jpg"/>
        <back  url="_9_57/2/2/%v_%u.jpg"/>
        <left  url="_9_57/3/2/%v_%u.jpg"/>
        <up    url="_9_57/4/2/%v_%u.jpg"/>
        <down  url="_9_57/5/2/%v_%u.jpg"/>
      </level>
      <level tiledimagewidth="1273" tiledimageheight="1273">
        <front url="_9_57/0/1/%v_%u.jpg"/>
        <right url="_9_57/1/1/%v_%u.jpg"/>
        <back  url="_9_57/2/1/%v_%u.jpg"/>
        <left  url="_9_57/3/1/%v_%u.jpg"/>
        <up    url="_9_57/4/1/%v_%u.jpg"/>
        <down  url="_9_57/5/1/%v_%u.jpg"/>
      </level>
      <level tiledimagewidth="636" tiledimageheight="636">
        <front url="_9_57/0/0/%v_%u.jpg"/>
        <right url="_9_57/1/0/%v_%u.jpg"/>
        <back  url="_9_57/2/0/%v_%u.jpg"/>
        <left  url="_9_57/3/0/%v_%u.jpg"/>
        <up    url="_9_57/4/0/%v_%u.jpg"/>
        <down  url="_9_57/5/0/%v_%u.jpg"/>
      </level>
    </image>


  <!-- **** 3 Point Spots **** -->

  <hotspot name="spotpoint90"
           ath="-161.815716" atv="-4.462740"
           visible="true"
           style="IconDefaultPointSpotStyle1"
           descriptionid=""
           onclick="onclickspotpoint90"
           />
  <hotspot name="spotpoint90" devices="flash" zorder="3"/>
  <hotspot name="spotpoint90" devices="html5+desktop" zorder="3" zorder2="1"/>
  <hotspot name="spotpoint90" devices="tablet|mobile" zorder2="1"/>
  <action name="onclickspotpoint90">
        mainloadscene(pano56);
      lookat(get(panoview.h), get(panoview.v), get(panoview.fov));
    
  </action>
  <hotspot name="spotpoint91"
           ath="57.624471" atv="-5.950438"
           visible="true"
           style="IconDefaultPointSpotStyle1"
           descriptionid=""
           onclick="onclickspotpoint91"
           />
  <hotspot name="spotpoint91" devices="flash" zorder="3"/>
  <hotspot name="spotpoint91" devices="html5+desktop" zorder="3" zorder2="1"/>
  <hotspot name="spotpoint91" devices="tablet|mobile" zorder2="1"/>
  <action name="onclickspotpoint91">
        mainloadscene(pano51);
      lookat(get(panoview.h), get(panoview.v), get(panoview.fov));
    
  </action>
  <hotspot name="spotpoint92"
           ath="-67.980244" atv="-8.282163"
           visible="true"
           style="IconDefaultPointSpotStyle1"
           descriptionid=""
           onclick="onclickspotpoint92"
           />
  <hotspot name="spotpoint92" devices="flash" zorder="3"/>
  <hotspot name="spotpoint92" devices="html5+desktop" zorder="3" zorder2="1"/>
  <hotspot name="spotpoint92" devices="tablet|mobile" zorder2="1"/>
  <action name="onclickspotpoint92">
        mainloadscene(pano46);
      lookat(get(panoview.h), get(panoview.v), get(panoview.fov));
    
  </action>
  <action name="hidepanopointspots">
    set(hotspot[spotpoint90].visible, false);
    set(hotspot[spotpoint91].visible, false);
    set(hotspot[spotpoint92].visible, false);
  </action>
  <action name="showpanopointspots">
    set(hotspot[spotpoint90].visible, true);
    set(hotspot[spotpoint91].visible, true);
    set(hotspot[spotpoint92].visible, true);
  </action>


  <action name="showpanospotsaction">
    if (tour_displayspots,
    showpanopointspots();
    );
  </action>
  <action name="hidepanospotsaction">
    hidepanopointspots();
  </action>

  <action name="setzorder2onstandardspots">
    if (device.html5,
      ifnot (device.desktop,


        tween(hotspot[spotpoint90].zorder2, %1, 0.5, default, copy(urlbckpspotpoint90, hotspot[spotpoint90].url); set(hotspot[spotpoint90].url, ""); copy(hotspot[spotpoint90].url, urlbckpspotpoint90););

        tween(hotspot[spotpoint91].zorder2, %1, 0.5, default, copy(urlbckpspotpoint91, hotspot[spotpoint91].url); set(hotspot[spotpoint91].url, ""); copy(hotspot[spotpoint91].url, urlbckpspotpoint91););

        tween(hotspot[spotpoint92].zorder2, %1, 0.5, default, copy(urlbckpspotpoint92, hotspot[spotpoint92].url); set(hotspot[spotpoint92].url, ""); copy(hotspot[spotpoint92].url, urlbckpspotpoint92););

      );
    );
  </action>  

</scene>


  <!-- Awake HTML5 plugins -->
  <events name="eventKrpanoLoadedEvts" onxmlcomplete="eventKrpanoLoadedAction();" keep="true" />
  <action name="eventKrpanoLoadedAction">
    
    set(events[eventKrpanoLoadedEvts].name, null);
    js(eventKrpanoLoaded());
  </action>

</krpano>